<?xml version="1.0" encoding="utf-8" ?>
<Defs>

	<RecipeDef>
		<defName>SplitDirt</defName>
		<label>extract sand and clay from dirt</label>
		<description>Separate the sand and the clay from a pile of dirt.</description>
		<jobString>Separating dirt.</jobString>
		<workSkillLearnFactor>0.25</workSkillLearnFactor>
		<effectWorking>CutStone</effectWorking>
		<soundWorking>Recipe_MakeStoneBlocks</soundWorking>
		<workAmount>400</workAmount>
		<ingredients>
			<li>
				<filter>
					<thingDefs>
						<li>PileofDirt</li>
					</thingDefs>
				</filter>
				<count>1</count>
			</li>
		</ingredients>
		<products>
			<RFFClay>1</RFFClay>
			<SandPile>1</SandPile>
		</products>
		<fixedIngredientFilter>
			<thingDefs>
				<li>PileofDirt</li>
			</thingDefs>
		</fixedIngredientFilter>
		<workSkill>Crafting</workSkill>
		<recipeUsers>
			<li>CraftingSpot</li>
		</recipeUsers>
	</RecipeDef>

	<RecipeDef>
		<defName>DirtToClay</defName>
		<label>convert 3 dirt to 4 clay</label>
		<description>Convert dirt directly into clay. (Produces a lower clay yield than splitting dirt into clay and sand and then grinding the sand into clay.)</description>
		<jobString>Creating clay.</jobString>
		<workSkillLearnFactor>0.25</workSkillLearnFactor>
		<effectWorking>CutStone</effectWorking>
		<soundWorking>Recipe_MakeStoneBlocks</soundWorking>
		<workAmount>1200</workAmount>
		<ingredients>
			<li>
				<filter>
					<thingDefs>
						<li>PileofDirt</li>
					</thingDefs>
				</filter>
				<count>3</count>
			</li>
		</ingredients>
		<products>
			<RFFClay>4</RFFClay>
		</products>
		<fixedIngredientFilter>
			<thingDefs>
				<li>PileofDirt</li>
			</thingDefs>
		</fixedIngredientFilter>
		<workSkill>Crafting</workSkill>
		<recipeUsers>
			<li>CraftingSpot</li>
		</recipeUsers>
	</RecipeDef>

	<RecipeDef>
		<defName>SplitDirt2</defName>
		<label>extract sand and clay from dirt</label>
		<description>Separate the sand and the clay from a pile of dirt.</description>
		<jobString>Separating dirt.</jobString>
		<workSkillLearnFactor>0.25</workSkillLearnFactor>
		<effectWorking>CutStone</effectWorking>
		<soundWorking>Recipe_MakeStoneBlocks</soundWorking>
		<workAmount>300</workAmount>
		<ingredients>
			<li>
				<filter>
					<thingDefs>
						<li>PileofDirt</li>
					</thingDefs>
				</filter>
				<count>1</count>
			</li>
		</ingredients>
		<products>
			<RFFClay>1</RFFClay>
			<SandPile>1</SandPile>
		</products>
		<fixedIngredientFilter>
			<thingDefs>
				<li>PileofDirt</li>
			</thingDefs>
		</fixedIngredientFilter>
		<workSkill>Crafting</workSkill>
		<recipeUsers>
			<li>RockMill</li>
		</recipeUsers>
	</RecipeDef>

	<RecipeDef>
		<defName>DirtToClay2</defName>
		<label>convert 3 dirt to 5 clay</label>
		<description>Convert dirt directly into clay. (Produces a lower clay yield than splitting dirt into clay and sand and then grinding the sand into clay.)</description>
		<jobString>Creating clay.</jobString>
		<workSkillLearnFactor>0.25</workSkillLearnFactor>
		<effectWorking>CutStone</effectWorking>
		<soundWorking>Recipe_MakeStoneBlocks</soundWorking>
		<workAmount>900</workAmount>
		<ingredients>
			<li>
				<filter>
					<thingDefs>
						<li>PileofDirt</li>
					</thingDefs>
				</filter>
				<count>3</count>
			</li>
		</ingredients>
		<products>
			<RFFClay>5</RFFClay>
		</products>
		<fixedIngredientFilter>
			<thingDefs>
				<li>PileofDirt</li>
			</thingDefs>
		</fixedIngredientFilter>
		<workSkill>Crafting</workSkill>
		<recipeUsers>
			<li>RockMill</li>
		</recipeUsers>
	</RecipeDef>
	
	<RecipeDef>
		<defName>MakeBricks</defName>
		<label>make 12 bricks</label>
		<description>Mold and fire clay to make bricks.</description>
		<jobString>Making bricks.</jobString>
		<workSpeedStat>SmeltingSpeed</workSpeedStat>
		<workSkillLearnFactor>0.25</workSkillLearnFactor>
		<effectWorking>Smelt</effectWorking>
		<soundWorking>Recipe_Smelt</soundWorking>
		<workAmount>2400</workAmount>
		<ingredients>
			<li>
				<filter>
					<thingDefs>
						<li>RFFClay</li>
					</thingDefs>
				</filter>
				<count>1</count>
			</li>
		</ingredients>
		<products>
			<RFFBricks>12</RFFBricks>
		</products>
		<fixedIngredientFilter>
			<thingDefs>
				<li>RFFClay</li>
			</thingDefs>
		</fixedIngredientFilter>
		<workSkill>Crafting</workSkill>
		<recipeUsers>
			<li>FueledSmithy</li>
			<li>ElectricSmithy</li>
		</recipeUsers>
	</RecipeDef>

	<RecipeDef>
		<defName>MakeFastBricks</defName>
		<label>make 24 bricks</label>
		<description>Mold and fire clay to make bricks.</description>
		<jobString>Making bricks.</jobString>
		<workSpeedStat>SmeltingSpeed</workSpeedStat>
		<workSkillLearnFactor>0.25</workSkillLearnFactor>
		<effectWorking>Smelt</effectWorking>
		<soundWorking>Recipe_Smelt</soundWorking>
		<workAmount>3600</workAmount>
		<ingredients>
			<li>
				<filter>
					<thingDefs>
						<li>RFFClay</li>
					</thingDefs>
				</filter>
				<count>2</count>
			</li>
		</ingredients>
		<products>
			<RFFBricks>24</RFFBricks>
		</products>
		<fixedIngredientFilter>
			<thingDefs>
				<li>RFFClay</li>
			</thingDefs>
		</fixedIngredientFilter>
		<workSkill>Crafting</workSkill>
		<recipeUsers>
			<li>ElectricSmelter</li>
		</recipeUsers>
	</RecipeDef>

	<RecipeDef>
		<defName>MakeCrushedRocksSlow</defName>
		<label>make 2 crushed rocks</label>
		<description>Break stone chunks into crushed rocks.</description>
		<jobString>Breaking up stone chunks.</jobString>
		<workSkillLearnFactor>0.25</workSkillLearnFactor>
		<effectWorking>CutStone</effectWorking>
		<soundWorking>Recipe_MakeStoneBlocks</soundWorking>
		<workAmount>1200</workAmount>
		<ingredients>
			<li>
				<filter>
					<categories>
						<li>StoneChunks</li>
					</categories>
				</filter>
				<count>1</count>
			</li>
		</ingredients>
		<products>
			<CrushedRocks>2</CrushedRocks>
		</products>
		<fixedIngredientFilter>
			<categories>
				<li>StoneChunks</li>
			</categories>
		</fixedIngredientFilter>
		<workSkill>Crafting</workSkill>
		<recipeUsers>
			<li>TableStonecutter</li>
		</recipeUsers>
	</RecipeDef>

	<RecipeDef>
		<defName>MakeCrushedRocksSlowBlock</defName>
		<label>make crushed rocks (from blocks)</label>
		<description>Break stone blocks into crushed rocks.</description>
		<jobString>Breaking up stone blocks.</jobString>
		<workSkillLearnFactor>0.25</workSkillLearnFactor>
		<effectWorking>CutStone</effectWorking>
		<soundWorking>Recipe_MakeStoneBlocks</soundWorking>
		<workAmount>600</workAmount>
		<ingredients>
			<li>
				<filter>
					<categories>
						<li>StoneBlocks</li>
					</categories>
				</filter>
				<count>10</count>
			</li>
		</ingredients>
		<products>
			<CrushedRocks>1</CrushedRocks>
		</products>
		<fixedIngredientFilter>
			<categories>
				<li>StoneBlocks</li>
			</categories>
		</fixedIngredientFilter>
		<workSkill>Crafting</workSkill>
		<recipeUsers>
			<li>TableStonecutter</li>
		</recipeUsers>
	</RecipeDef>
	
	<RecipeDef>
		<defName>MakeSandSlow</defName>
		<label>make sand</label>
		<description>Further break up crushed rocks to create sand.</description>
		<jobString>Making sand.</jobString>
		<workSkillLearnFactor>0.25</workSkillLearnFactor>
		<effectWorking>CutStone</effectWorking>
		<soundWorking>Recipe_MakeStoneBlocks</soundWorking>
		<workAmount>1200</workAmount>
		<ingredients>
			<li>
				<filter>
					<thingDefs>
						<li>CrushedRocks</li>
					</thingDefs>
				</filter>
				<count>1</count>
			</li>
		</ingredients>
		<products>
			<SandPile>1</SandPile>
		</products>
		<fixedIngredientFilter>
			<thingDefs>
				<li>CrushedRocks</li>
			</thingDefs>
		</fixedIngredientFilter>
		<workSkill>Crafting</workSkill>
		<recipeUsers>
			<li>TableStonecutter</li>
		</recipeUsers>
	</RecipeDef>
	
	<RecipeDef>
		<defName>MakeCrushedRocks</defName>
		<label>make 2 crushed rocks</label>
		<description>Break stone chunks into crushed rocks.</description>
		<jobString>Breaking up stone chunks.</jobString>
		<workSkillLearnFactor>0.25</workSkillLearnFactor>
		<effectWorking>CutStone</effectWorking>
		<soundWorking>Recipe_MakeStoneBlocks</soundWorking>
		<workAmount>400</workAmount>
		<ingredients>
			<li>
				<filter>
					<categories>
						<li>StoneChunks</li>
					</categories>
				</filter>
				<count>1</count>
			</li>
		</ingredients>
		<products>
			<CrushedRocks>2</CrushedRocks>
		</products>
		<fixedIngredientFilter>
			<categories>
				<li>StoneChunks</li>
			</categories>
		</fixedIngredientFilter>
		<workSkill>Crafting</workSkill>
		<recipeUsers>
			<li>RockMill</li>
		</recipeUsers>
	</RecipeDef>

	<RecipeDef>
		<defName>MakeCrushedRocksBlock</defName>
		<label>make crushed rocks (from blocks)</label>
		<description>Break stone blocks into crushed rocks.</description>
		<jobString>Breaking up stone blocks.</jobString>
		<workSkillLearnFactor>0.25</workSkillLearnFactor>
		<effectWorking>CutStone</effectWorking>
		<soundWorking>Recipe_MakeStoneBlocks</soundWorking>
		<workAmount>200</workAmount>
		<ingredients>
			<li>
				<filter>
					<categories>
						<li>StoneBlocks</li>
					</categories>
				</filter>
				<count>10</count>
			</li>
		</ingredients>
		<products>
			<CrushedRocks>1</CrushedRocks>
		</products>
		<fixedIngredientFilter>
			<categories>
				<li>StoneBlocks</li>
			</categories>
		</fixedIngredientFilter>
		<workSkill>Crafting</workSkill>
		<recipeUsers>
			<li>RockMill</li>
		</recipeUsers>
	</RecipeDef>

	<RecipeDef>
		<defName>MakeSand</defName>
		<label>make sand</label>
		<description>Further break up crushed rocks to create sand.</description>
		<jobString>Making sand.</jobString>
		<workSkillLearnFactor>0.25</workSkillLearnFactor>
		<effectWorking>CutStone</effectWorking>
		<soundWorking>Recipe_MakeStoneBlocks</soundWorking>
		<workAmount>400</workAmount>
		<ingredients>
			<li>
				<filter>
					<thingDefs>
						<li>CrushedRocks</li>
					</thingDefs>
				</filter>
				<count>1</count>
			</li>
		</ingredients>
		<products>
			<SandPile>1</SandPile>
		</products>
		<fixedIngredientFilter>
			<thingDefs>
				<li>CrushedRocks</li>
			</thingDefs>
		</fixedIngredientFilter>
		<workSkill>Crafting</workSkill>
		<recipeUsers>
			<li>RockMill</li>
		</recipeUsers>
	</RecipeDef>

	<RecipeDef>
		<defName>MakeClay</defName>
		<label>make clay</label>
		<description>Grind sand up into even finer particles, to create clay.</description>
		<jobString>Making clay.</jobString>
		<workSkillLearnFactor>0.25</workSkillLearnFactor>
		<effectWorking>CutStone</effectWorking>
		<soundWorking>Recipe_MakeStoneBlocks</soundWorking>
		<workAmount>400</workAmount>
		<ingredients>
			<li>
				<filter>
					<thingDefs>
						<li>SandPile</li>
					</thingDefs>
				</filter>
				<count>1</count>
			</li>
		</ingredients>
		<products>
			<RFFClay>1</RFFClay>
		</products>
		<fixedIngredientFilter>
			<thingDefs>
				<li>SandPile</li>
			</thingDefs>
		</fixedIngredientFilter>
		<workSkill>Crafting</workSkill>
		<recipeUsers>
			<li>RockMill</li>
		</recipeUsers>
	</RecipeDef>
	
	<RecipeDef>
		<defName>MakeDirt</defName>
		<label>make 2 dirt</label>
		<description>Create dirt from sand, clay and fertilizer.</description>
		<jobString>Creating dirt.</jobString>
		<workSkillLearnFactor>0.25</workSkillLearnFactor>
		<effectWorking>CutStone</effectWorking>
		<soundWorking>Recipe_MakeStoneBlocks</soundWorking>
		<workAmount>400</workAmount>
		<ingredients>
			<li>
				<filter>
					<thingDefs>
						<li>RFFClay</li>
					</thingDefs>
				</filter>
				<count>1</count>
			</li>
			<li>
				<filter>
					<thingDefs>
						<li>SandPile</li>
					</thingDefs>
				</filter>
				<count>1</count>
			</li>
			<li>
				<filter>
					<thingDefs>
						<li>Fertilizer</li>
					</thingDefs>
				</filter>
				<count>1</count>
			</li>
		</ingredients>
		<products>
			<PileofDirt>2</PileofDirt>
		</products>
		<fixedIngredientFilter>
			<thingDefs>
				<li>RFFClay</li>
				<li>SandPile</li>
				<li>Fertilizer</li>
			</thingDefs>
		</fixedIngredientFilter>
		<workSkill>Crafting</workSkill>
		<recipeUsers>
			<li>CraftingSpot</li>
		</recipeUsers>
	</RecipeDef>

	<RecipeDef>
		<defName>MakeDirtEfficient</defName>
		<label>make 2 dirt</label>
		<description>Create dirt from sand, clay and fertilizer.</description>
		<jobString>Creating dirt.</jobString>
		<workSkillLearnFactor>0.25</workSkillLearnFactor>
		<effectWorking>CutStone</effectWorking>
		<soundWorking>Recipe_MakeStoneBlocks</soundWorking>
		<workAmount>300</workAmount>
		<ingredients>
			<li>
				<filter>
					<thingDefs>
						<li>RFFClay</li>
					</thingDefs>
				</filter>
				<count>1</count>
			</li>
			<li>
				<filter>
					<thingDefs>
						<li>SandPile</li>
					</thingDefs>
				</filter>
				<count>1</count>
			</li>
			<li>
				<filter>
					<thingDefs>
						<li>Fertilizer</li>
					</thingDefs>
				</filter>
				<count>1</count>
			</li>
		</ingredients>
		<products>
			<PileofDirt>2</PileofDirt>
		</products>
		<fixedIngredientFilter>
			<thingDefs>
				<li>RFFClay</li>
				<li>SandPile</li>
				<li>Fertilizer</li>
			</thingDefs>
		</fixedIngredientFilter>
		<workSkill>Crafting</workSkill>
		<recipeUsers>
			<li>RockMill</li>
		</recipeUsers>
	</RecipeDef>

	<RecipeDef>
		<defName>MakeCrushedRocks5</defName>
		<label>make 10 crushed rocks</label>
		<description>Break stone chunks into crushed rocks.</description>
		<jobString>Breaking up stone chunks.</jobString>
		<workSkillLearnFactor>0.25</workSkillLearnFactor>
		<effectWorking>CutStone</effectWorking>
		<soundWorking>Recipe_MakeStoneBlocks</soundWorking>
		<workAmount>1000</workAmount>
		<ingredients>
			<li>
				<filter>
					<categories>
						<li>StoneChunks</li>
					</categories>
				</filter>
				<count>5</count>
			</li>
		</ingredients>
		<products>
			<CrushedRocks>10</CrushedRocks>
		</products>
		<fixedIngredientFilter>
			<categories>
				<li>StoneChunks</li>
			</categories>
		</fixedIngredientFilter>
		<workSkill>Crafting</workSkill>
		<recipeUsers>
			<li>RockMill</li>
		</recipeUsers>
	</RecipeDef>

	<RecipeDef>
		<defName>MakeSand5</defName>
		<label>make 5 sand</label>
		<description>Further break up crushed rocks to create sand.</description>
		<jobString>Making sand.</jobString>
		<workSkillLearnFactor>0.25</workSkillLearnFactor>
		<effectWorking>CutStone</effectWorking>
		<soundWorking>Recipe_MakeStoneBlocks</soundWorking>
		<workAmount>1000</workAmount>
		<ingredients>
			<li>
				<filter>
					<thingDefs>
						<li>CrushedRocks</li>
					</thingDefs>
				</filter>
				<count>5</count>
			</li>
		</ingredients>
		<products>
			<SandPile>5</SandPile>
		</products>
		<fixedIngredientFilter>
			<thingDefs>
				<li>CrushedRocks</li>
			</thingDefs>
		</fixedIngredientFilter>
		<workSkill>Crafting</workSkill>
		<recipeUsers>
			<li>RockMill</li>
		</recipeUsers>
	</RecipeDef>

	<RecipeDef>
		<defName>MakeClay5</defName>
		<label>make 5 clay</label>
		<description>Grind sand up into even finer particles, to create clay.</description>
		<jobString>Making clay.</jobString>
		<workSkillLearnFactor>0.25</workSkillLearnFactor>
		<effectWorking>CutStone</effectWorking>
		<soundWorking>Recipe_MakeStoneBlocks</soundWorking>
		<workAmount>1000</workAmount>
		<ingredients>
			<li>
				<filter>
					<thingDefs>
						<li>SandPile</li>
					</thingDefs>
				</filter>
				<count>5</count>
			</li>
		</ingredients>
		<products>
			<RFFClay>5</RFFClay>
		</products>
		<fixedIngredientFilter>
			<thingDefs>
				<li>SandPile</li>
			</thingDefs>
		</fixedIngredientFilter>
		<workSkill>Crafting</workSkill>
		<recipeUsers>
			<li>RockMill</li>
		</recipeUsers>
	</RecipeDef>
	
	<RecipeDef>
		<defName>MakeDirt5</defName>
		<label>make 10 dirt</label>
		<description>Create dirt from sand, clay and fertilizer.</description>
		<jobString>Creating dirt.</jobString>
		<workSkillLearnFactor>0.25</workSkillLearnFactor>
		<effectWorking>CutStone</effectWorking>
		<soundWorking>Recipe_MakeStoneBlocks</soundWorking>
		<workAmount>1000</workAmount>
		<ingredients>
			<li>
				<filter>
					<thingDefs>
						<li>RFFClay</li>
					</thingDefs>
				</filter>
				<count>5</count>
			</li>
			<li>
				<filter>
					<thingDefs>
						<li>SandPile</li>
					</thingDefs>
				</filter>
				<count>5</count>
			</li>
			<li>
				<filter>
					<thingDefs>
						<li>Fertilizer</li>
					</thingDefs>
				</filter>
				<count>5</count>
			</li>
		</ingredients>
		<products>
			<PileofDirt>10</PileofDirt>
		</products>
		<fixedIngredientFilter>
			<thingDefs>
				<li>RFFClay</li>
				<li>SandPile</li>
				<li>Fertilizer</li>
			</thingDefs>
		</fixedIngredientFilter>
		<workSkill>Crafting</workSkill>
		<recipeUsers>
			<li>CraftingSpot</li>
		</recipeUsers>
	</RecipeDef>
	
	<RecipeDef>
		<defName>MakeDirt5Efficient</defName>
		<label>make 10 dirt</label>
		<description>Create dirt from sand, clay and fertilizer.</description>
		<jobString>Creating dirt.</jobString>
		<workSkillLearnFactor>0.25</workSkillLearnFactor>
		<effectWorking>CutStone</effectWorking>
		<soundWorking>Recipe_MakeStoneBlocks</soundWorking>
		<workAmount>750</workAmount>
		<ingredients>
			<li>
				<filter>
					<thingDefs>
						<li>RFFClay</li>
					</thingDefs>
				</filter>
				<count>5</count>
			</li>
			<li>
				<filter>
					<thingDefs>
						<li>SandPile</li>
					</thingDefs>
				</filter>
				<count>5</count>
			</li>
			<li>
				<filter>
					<thingDefs>
						<li>Fertilizer</li>
					</thingDefs>
				</filter>
				<count>5</count>
			</li>
		</ingredients>
		<products>
			<PileofDirt>10</PileofDirt>
		</products>
		<fixedIngredientFilter>
			<thingDefs>
				<li>RFFClay</li>
				<li>SandPile</li>
				<li>Fertilizer</li>
			</thingDefs>
		</fixedIngredientFilter>
		<workSkill>Crafting</workSkill>
		<recipeUsers>
			<li>RockMill</li>
		</recipeUsers>
	</RecipeDef>
	
	<RecipeDef>
		<defName>MakeCompost</defName>
		<label>make raw compost</label>
		<description>Make raw compost from organic waste (raw meat and plants).</description>
		<jobString>Making raw compost.</jobString>
		<workSpeedStat>CookSpeed</workSpeedStat>
		<workSkillLearnFactor>0.25</workSkillLearnFactor>
		<effectWorking>Cook</effectWorking>
		<soundWorking>Recipe_CookMeal</soundWorking>
		<allowMixingIngredients>true</allowMixingIngredients>
		<workAmount>250</workAmount>
		<ingredientValueGetterClass>RFF_Code.IngredientValueGetter_Mass</ingredientValueGetterClass>
		<ingredients>
			<li>
				<filter>
					<categories>
						<li>FoodRaw</li>
					</categories>
					<thingDefs>
						<li>Hay</li>
						<li>RottedMush</li>
						<li>PlantScraps</li>
						<li>Kibble</li>
						<li>Pemmican</li>
					</thingDefs>
				</filter>
				<count>.5</count>
			</li>
		</ingredients>
		<products>
			<RawCompost>1</RawCompost>
		</products>
		<fixedIngredientFilter>
			<categories>
				<li>FoodRaw</li>
			</categories>
			<thingDefs>
				<li>Hay</li>
				<li>RottedMush</li>
				<li>PlantScraps</li>
				<li>Kibble</li>
				<li>Pemmican</li>
			</thingDefs>
		</fixedIngredientFilter>
		<defaultIngredientFilter>
			<categories>
				<li>FoodRaw</li>
			</categories>
			<thingDefs>
				<li>Hay</li>
				<li>RottedMush</li>
				<li>PlantScraps</li>
			</thingDefs>
		</defaultIngredientFilter>
		<workSkill>Cooking</workSkill>
  		<recipeUsers>
			<li>TableButcher</li>
		</recipeUsers>
	</RecipeDef>

	<RecipeDef>
		<defName>MakeCompost5</defName>
		<label>make 5 raw compost</label>
		<description>Make raw compost from organic waste (raw meat and plants).</description>
		<jobString>Making raw compost.</jobString>
		<workSpeedStat>CookSpeed</workSpeedStat>
		<workSkillLearnFactor>0.5</workSkillLearnFactor>
		<effectWorking>Cook</effectWorking>
		<soundWorking>Recipe_CookMeal</soundWorking>
		<allowMixingIngredients>true</allowMixingIngredients>
		<workAmount>625</workAmount>
		<ingredientValueGetterClass>RFF_Code.IngredientValueGetter_Mass</ingredientValueGetterClass>
		<ingredients>
			<li>
				<filter>
					<categories>
						<li>FoodRaw</li>
					</categories>
					<thingDefs>
						<li>Hay</li>
						<li>RottedMush</li>
						<li>PlantScraps</li>
						<li>Kibble</li>
						<li>Pemmican</li>
					</thingDefs>
				</filter>
				<count>2.5</count>
			</li>
		</ingredients>
		<products>
			<RawCompost>5</RawCompost>
		</products>
		<fixedIngredientFilter>
			<categories>
				<li>FoodRaw</li>
			</categories>
			<thingDefs>
				<li>Hay</li>
				<li>RottedMush</li>
				<li>PlantScraps</li>
				<li>Kibble</li>
				<li>Pemmican</li>
			</thingDefs>
		</fixedIngredientFilter>
		<defaultIngredientFilter>
			<categories>
				<li>FoodRaw</li>
			</categories>
			<thingDefs>
				<li>Hay</li>
				<li>RottedMush</li>
				<li>PlantScraps</li>
			</thingDefs>
		</defaultIngredientFilter>
		<workSkill>Cooking</workSkill>
  		<recipeUsers>
			<li>TableButcher</li>
		</recipeUsers>
	</RecipeDef>

	<RecipeDef>
		<defName>CompostCorpse</defName>
		<label>burn corpse for compost</label>
		<description>Cremate a corpse into compost.</description>
		<jobString>Cremating.</jobString>
		<workAmount>450</workAmount>
		<effectWorking>Cremate</effectWorking>
		<soundWorking>Recipe_Cremate</soundWorking>
		<allowMixingIngredients>true</allowMixingIngredients>
		<ingredientValueGetterClass>RFF_Code.IngredientValueGetter_Mass</ingredientValueGetterClass>
		<ingredients>
			<li>
				<filter>
					<categories>
						<li>Corpses</li>
					</categories>
				</filter>
				<count>50</count>
			</li>
		</ingredients>
		<products>
			<RawCompost>5</RawCompost>
		</products>
		<fixedIngredientFilter>
			<categories>
				<li>Corpses</li>
			</categories>
			<disallowedCategories>
				<li>CorpsesMechanoid</li>
			</disallowedCategories>
		</fixedIngredientFilter>
		<defaultIngredientFilter>
			<categories>
				<li>CorpsesHumanlike</li>
			</categories>
			<specialFiltersToAllow>
				<li>AllowCorpsesColonist</li>
				<li>AllowCorpsesStranger</li>
			</specialFiltersToAllow>
		</defaultIngredientFilter>
		<recipeUsers>
			<li>ElectricCrematorium</li>
		</recipeUsers>
	</RecipeDef>

	<RecipeDef>
		<defName>CompostCorpseCampfire</defName>
		<label>burn corpse for compost</label>
		<description>Cremate a corpse into compost at a campfire. Less efficient than doing so in a crematorium.</description>
		<jobString>Cremating.</jobString>
		<workAmount>1350</workAmount>
		<effectWorking>Cremate</effectWorking>
		<soundWorking>Recipe_Cremate</soundWorking>
		<allowMixingIngredients>true</allowMixingIngredients>
		<ingredientValueGetterClass>RFF_Code.IngredientValueGetter_Mass</ingredientValueGetterClass>
		<ingredients>
			<li>
				<filter>
					<categories>
						<li>Corpses</li>
					</categories>
				</filter>
				<count>50</count>
			</li>
		</ingredients>
		<products>
			<RawCompost>4</RawCompost>
		</products>
		<fixedIngredientFilter>
			<categories>
				<li>Corpses</li>
			</categories>
			<disallowedCategories>
				<li>CorpsesMechanoid</li>
			</disallowedCategories>
		</fixedIngredientFilter>
		<defaultIngredientFilter>
			<categories>
				<li>CorpsesHumanlike</li>
			</categories>
			<specialFiltersToAllow>
				<li>AllowCorpsesColonist</li>
				<li>AllowCorpsesStranger</li>
			</specialFiltersToAllow>
		</defaultIngredientFilter>
		<recipeUsers>
			<li>Campfire</li>
		</recipeUsers>
	</RecipeDef>
	
	<RecipeDef Name="RFF_MakeStoneBlocksBase" Abstract="True">
		<jobString>Cutting stone blocks from chunk.</jobString>
		<workAmount>1200</workAmount>
		<workSpeedStat>UnskilledLaborSpeed</workSpeedStat>
		<effectWorking>CutStone</effectWorking>
		<soundWorking>Recipe_MakeStoneBlocks</soundWorking>
		<targetCountAdjustment>20</targetCountAdjustment>
		<recipeUsers>
			<li>RockMill</li>
		</recipeUsers>
	</RecipeDef>

	<RecipeDef ParentName="RFF_MakeStoneBlocksBase">
		<defName>Make_StoneBlocksAnyRM</defName>
		<label>make any stone blocks</label>
		<description>Cut rock chunks into usable stone blocks.</description>
		<workerCounterClass>RecipeWorkerCounter_MakeStoneBlocks</workerCounterClass>
		<ingredients>
			<li>
				<filter>
					<categories>
						<li>StoneChunks</li>
					</categories>
				</filter>
				<count>1</count>
			</li>
		</ingredients>
		<fixedIngredientFilter>
			<categories>
				<li>StoneChunks</li>
			</categories>
		</fixedIngredientFilter>
		<specialProducts>
			<li>Butchery</li>
		</specialProducts>
	</RecipeDef>
	
	<RecipeDef ParentName="RFF_MakeStoneBlocksBase">
		<defName>Make_StoneBlocksSandstoneRM</defName>
		<label>make sandstone blocks</label>
		<description>Cuts sandstone chunks into usable blocks.</description>
		<ingredients>
			<li>
				<filter>
					<thingDefs>
						<li>ChunkSandstone</li>
					</thingDefs>
				</filter>
				<count>1</count>
			</li>
		</ingredients>
		<fixedIngredientFilter>
			<thingDefs>
				<li>ChunkSandstone</li>
			</thingDefs>
		</fixedIngredientFilter>
		<products>
			<BlocksSandstone>20</BlocksSandstone>
		</products>
	</RecipeDef>
	
	<RecipeDef ParentName="RFF_MakeStoneBlocksBase">
		<defName>Make_StoneBlocksGraniteRM</defName>
		<label>make granite blocks</label>
		<description>Cuts granite chunks into usable blocks.</description>
		<ingredients>
			<li>
				<filter>
					<thingDefs>
						<li>ChunkGranite</li>
					</thingDefs>
				</filter>
				<count>1</count>
			</li>
		</ingredients>
		<fixedIngredientFilter>
			<thingDefs>
				<li>ChunkGranite</li>
			</thingDefs>
		</fixedIngredientFilter>
		<products>
			<BlocksGranite>20</BlocksGranite>
		</products>
	</RecipeDef>	

	<RecipeDef ParentName="RFF_MakeStoneBlocksBase">
		<defName>Make_StoneBlocksLimestoneRM</defName>
		<label>make limestone blocks</label>
		<description>Cuts limestone chunks into usable blocks.</description>
		<ingredients>
			<li>
				<filter>
					<thingDefs>
						<li>ChunkLimestone</li>
					</thingDefs>
				</filter>
				<count>1</count>
			</li>
		</ingredients>
		<fixedIngredientFilter>
			<thingDefs>
				<li>ChunkLimestone</li>
			</thingDefs>
		</fixedIngredientFilter>
		<products>
			<BlocksLimestone>20</BlocksLimestone>
		</products>
	</RecipeDef>	
	
	<RecipeDef ParentName="RFF_MakeStoneBlocksBase">
		<defName>Make_StoneBlocksSlateRM</defName>
		<label>make slate blocks</label>
		<description>Cuts slate chunks into usable blocks.</description>
		<ingredients>
			<li>
				<filter>
					<thingDefs>
						<li>ChunkSlate</li>
					</thingDefs>
				</filter>
				<count>1</count>
			</li>
		</ingredients>
		<fixedIngredientFilter>
			<thingDefs>
				<li>ChunkSlate</li>
			</thingDefs>
		</fixedIngredientFilter>
		<products>
			<BlocksSlate>20</BlocksSlate>
		</products>
	</RecipeDef>

	<RecipeDef ParentName="RFF_MakeStoneBlocksBase">
		<defName>Make_StoneBlocksMarbleRM</defName>
		<label>make marble blocks</label>
		<description>Cuts marble chunks into usable blocks.</description>
		<ingredients>
			<li>
				<filter>
					<thingDefs>
						<li>ChunkMarble</li>
					</thingDefs>
				</filter>
				<count>1</count>
			</li>
		</ingredients>
		<fixedIngredientFilter>
			<thingDefs>
				<li>ChunkMarble</li>
			</thingDefs>
		</fixedIngredientFilter>
		<products>
			<BlocksMarble>20</BlocksMarble>
		</products>
	</RecipeDef>	
	
</Defs>
